<PAMDataset>
  <PAMRasterBand band="1">
    <NoDataValue le_hex_equiv="000000000000F8FF">nan</NoDataValue>
    <ColorInterp>Palette</ColorInterp>
    <ColorTable>
      <Entry c1="0" c2="0" c3="0" c4="0" />
      <Entry c1="0" c2="0" c3="0" c4="0" />
      <Entry c1="0" c2="0" c3="0" c4="0" />
      <Entry c1="0" c2="0" c3="0" c4="0" />
      <Entry c1="0" c2="0" c3="0" c4="0" />
      <Entry c1="0" c2="0" c3="0" c4="0" />
      <Entry c1="0" c2="0" c3="0" c4="0" />
      <Entry c1="0" c2="0" c3="0" c4="0" />
      <Entry c1="0" c2="0" c3="0" c4="0" />
      <Entry c1="0" c2="0" c3="0" c4="0" />
      <Entry c1="0" c2="0" c3="0" c4="0" />
      <Entry c1="0" c2="0" c3="0" c4="0" />
      <Entry c1="0" c2="0" c3="0" c4="0" />
      <Entry c1="229" c2="255" c3="0" c4="255" />
      <Entry c1="184" c2="255" c3="0" c4="255" />
      <Entry c1="138" c2="255" c3="0" c4="255" />
      <Entry c1="93" c2="255" c3="0" c4="255" />
      <Entry c1="48" c2="255" c3="0" c4="255" />
      <Entry c1="2" c2="255" c3="0" c4="255" />
      <Entry c1="0" c2="255" c3="43" c4="255" />
      <Entry c1="0" c2="255" c3="89" c4="255" />
      <Entry c1="0" c2="255" c3="134" c4="255" />
      <Entry c1="0" c2="255" c3="180" c4="255" />
      <Entry c1="0" c2="255" c3="225" c4="255" />
      <Entry c1="0" c2="239" c3="255" c4="255" />
      <Entry c1="0" c2="194" c3="255" c4="255" />
      <Entry c1="0" c2="148" c3="255" c4="255" />
      <Entry c1="0" c2="103" c3="255" c4="255" />
      <Entry c1="0" c2="57" c3="255" c4="255" />
      <Entry c1="0" c2="12" c3="255" c4="255" />
      <Entry c1="34" c2="0" c3="255" c4="255" />
      <Entry c1="79" c2="0" c3="255" c4="255" />
      <Entry c1="125" c2="0" c3="255" c4="255" />
      <Entry c1="170" c2="0" c3="255" c4="255" />
      <Entry c1="216" c2="0" c3="255" c4="255" />
      <Entry c1="255" c2="0" c3="249" c4="255" />
      <Entry c1="255" c2="0" c3="204" c4="255" />
      <Entry c1="255" c2="0" c3="158" c4="255" />
      <Entry c1="255" c2="0" c3="113" c4="255" />
      <Entry c1="255" c2="0" c3="67" c4="255" />
    </ColorTable>
    <Metadata>
      <MDI key="COLOR_TABLE_RULE_RGB_0">1.242598e+01 1.803390e+01 255 255 0 0 255 0</MDI>
      <MDI key="COLOR_TABLE_RULE_RGB_1">1.803390e+01 2.364182e+01 0 255 0 0 255 255</MDI>
      <MDI key="COLOR_TABLE_RULE_RGB_2">2.364182e+01 2.924973e+01 0 255 255 0 0 255</MDI>
      <MDI key="COLOR_TABLE_RULE_RGB_3">2.924973e+01 3.485765e+01 0 0 255 255 0 255</MDI>
      <MDI key="COLOR_TABLE_RULE_RGB_4">3.485765e+01 4.046556e+01 255 0 255 255 0 0</MDI>
      <MDI key="COLOR_TABLE_RULES_COUNT">5</MDI>
    </Metadata>
  </PAMRasterBand>
</PAMDataset>
